{
  "generated_at": "2026-06-30T23:41:40.162229",
  "horizon": 5,
  "data_source": "open_meteo_era5",
  "cities": {
    "Mumbai": {
      "lat": 19.11,
      "lon": 72.85,
      "horizons": [
        {
          "horizon": 1,
          "forecast_date": "2026-07-01",
          "forecasts": {
            "PRmsl": {
              "uv_HLSTM_GRU": 100543.871,
              "uv_GRU": 100480.7545,
              "uv_ANN": 100505.2232,
              "mv_HLSTM_GRU": 100660.8697,
              "mv_GRU": 100487.9278,
              "mv_ANN": 100454.0683,
              "ensemble_uv": 100509.9495,
              "ensemble_mv": 100534.2886,
              "ensemble_all": 100522.1191,
              "unit": "Pa"
            },
            "RH2m": {
              "uv_HLSTM_GRU": 84.8253,
              "uv_GRU": 83.0104,
              "uv_ANN": 83.5819,
              "mv_HLSTM_GRU": 82.1428,
              "mv_GRU": 82.967,
              "mv_ANN": 83.325,
              "ensemble_uv": 83.8059,
              "ensemble_mv": 82.8116,
              "ensemble_all": 83.3087,
              "unit": "%"
            },
            "TMP2m": {
              "uv_HLSTM_GRU": 28.6566,
              "uv_GRU": 28.5486,
              "uv_ANN": 27.5885,
              "mv_HLSTM_GRU": 28.5954,
              "mv_GRU": 28.5952,
              "mv_ANN": 27.9296,
              "ensemble_uv": 28.2646,
              "ensemble_mv": 28.3734,
              "ensemble_all": 28.319,
              "unit": "C"
            }
          }
        },
        {
          "horizon": 2,
          "forecast_date": "2026-07-02",
          "forecasts": {
            "PRmsl": {
              "uv_HLSTM_GRU": 100559.1471,
              "uv_GRU": 100511.9138,
              "uv_ANN": 100533.3444,
              "mv_HLSTM_GRU": 100629.5867,
              "mv_GRU": 100478.1116,
              "mv_ANN": 100436.9681,
              "ensemble_uv": 100534.8017,
              "ensemble_mv": 100514.8888,
              "ensemble_all": 100524.8453,
              "unit": "Pa"
            },
            "RH2m": {
              "uv_HLSTM_GRU": 78.0353,
              "uv_GRU": 77.9664,
              "uv_ANN": 77.2391,
              "mv_HLSTM_GRU": 77.4152,
              "mv_GRU": 79.1577,
              "mv_ANN": 78.5025,
              "ensemble_uv": 77.747,
              "ensemble_mv": 78.3585,
              "ensemble_all": 78.0527,
              "unit": "%"
            },
            "TMP2m": {
              "uv_HLSTM_GRU": 29.6381,
              "uv_GRU": 29.5564,
              "uv_ANN": 28.9879,
              "mv_HLSTM_GRU": 29.5492,
              "mv_GRU": 29.1751,
              "mv_ANN": 28.3651,
              "ensemble_uv": 29.3941,
              "ensemble_mv": 29.0298,
              "ensemble_all": 29.212,
              "unit": "C"
            }
          }
        },
        {
          "horizon": 3,
          "forecast_date": "2026-07-03",
          "forecasts": {
            "PRmsl": {
              "uv_HLSTM_GRU": 100556.0333,
              "uv_GRU": 100502.122,
              "uv_ANN": 100546.9417,
              "mv_HLSTM_GRU": 100599.1768,
              "mv_GRU": 100475.2293,
              "mv_ANN": 100425.9641,
              "ensemble_uv": 100535.0323,
              "ensemble_mv": 100500.1234,
              "ensemble_all": 100517.5779,
              "unit": "Pa"
            },
            "RH2m": {
              "uv_HLSTM_GRU": 73.5376,
              "uv_GRU": 74.0306,
              "uv_ANN": 72.0341,
              "mv_HLSTM_GRU": 75.7824,
              "mv_GRU": 77.397,
              "mv_ANN": 75.4182,
              "ensemble_uv": 73.2008,
              "ensemble_mv": 76.1992,
              "ensemble_all": 74.7,
              "unit": "%"
            },
            "TMP2m": {
              "uv_HLSTM_GRU": 30.3664,
              "uv_GRU": 30.2668,
              "uv_ANN": 29.6357,
              "mv_HLSTM_GRU": 29.977,
              "mv_GRU": 29.4592,
              "mv_ANN": 28.8428,
              "ensemble_uv": 30.0896,
              "ensemble_mv": 29.4264,
              "ensemble_all": 29.758,
              "unit": "C"
            }
          }
        },
        {
          "horizon": 4,
          "forecast_date": "2026-07-04",
          "forecasts": {
            "PRmsl": {
              "uv_HLSTM_GRU": 100554.8038,
              "uv_GRU": 100500.7813,
              "uv_ANN": 100536.1942,
              "mv_HLSTM_GRU": 100571.5414,
              "mv_GRU": 100447.9101,
              "mv_ANN": 100420.5479,
              "ensemble_uv": 100530.5931,
              "ensemble_mv": 100479.9998,
              "ensemble_all": 100505.2964,
              "unit": "Pa"
            },
            "RH2m": {
              "uv_HLSTM_GRU": 71.0582,
              "uv_GRU": 71.5119,
              "uv_ANN": 69.1597,
              "mv_HLSTM_GRU": 75.2221,
              "mv_GRU": 76.707,
              "mv_ANN": 74.1815,
              "ensemble_uv": 70.5766,
              "ensemble_mv": 75.3702,
              "ensemble_all": 72.9734,
              "unit": "%"
            },
            "TMP2m": {
              "uv_HLSTM_GRU": 30.479,
              "uv_GRU": 30.4346,
              "uv_ANN": 30.0455,
              "mv_HLSTM_GRU": 29.9402,
              "mv_GRU": 29.3841,
              "mv_ANN": 28.9726,
              "ensemble_uv": 30.3197,
              "ensemble_mv": 29.4323,
              "ensemble_all": 29.876,
              "unit": "C"
            }
          }
        },
        {
          "horizon": 5,
          "forecast_date": "2026-07-05",
          "forecasts": {
            "PRmsl": {
              "uv_HLSTM_GRU": 100547.6109,
              "uv_GRU": 100492.2999,
              "uv_ANN": 100509.7643,
              "mv_HLSTM_GRU": 100548.9347,
              "mv_GRU": 100448.2955,
              "mv_ANN": 100417.6534,
              "ensemble_uv": 100516.5584,
              "ensemble_mv": 100471.6278,
              "ensemble_all": 100494.0931,
              "unit": "Pa"
            },
            "RH2m": {
              "uv_HLSTM_GRU": 71.3236,
              "uv_GRU": 71.044,
              "uv_ANN": 67.8587,
              "mv_HLSTM_GRU": 75.3554,
              "mv_GRU": 76.6556,
              "mv_ANN": 74.2376,
              "ensemble_uv": 70.0754,
              "ensemble_mv": 75.4162,
              "ensemble_all": 72.7458,
              "unit": "%"
            },
            "TMP2m": {
              "uv_HLSTM_GRU": 30.1895,
              "uv_GRU": 30.1117,
              "uv_ANN": 29.9122,
              "mv_HLSTM_GRU": 29.6443,
              "mv_GRU": 29.0565,
              "mv_ANN": 28.8387,
              "ensemble_uv": 30.0711,
              "ensemble_mv": 29.1799,
              "ensemble_all": 29.6255,
              "unit": "C"
            }
          }
        }
      ]
    },
    "Delhi": {
      "lat": 28.61,
      "lon": 77.2,
      "horizons": [
        {
          "horizon": 1,
          "forecast_date": "2026-07-01",
          "forecasts": {
            "PRmsl": {
              "uv_HLSTM_GRU": 100237.612,
              "uv_GRU": 100223.8453,
              "uv_ANN": 100186.678,
              "mv_HLSTM_GRU": 99720.3492,
              "mv_GRU": 99275.3276,
              "mv_ANN": 99967.4876,
              "ensemble_uv": 100216.0451,
              "ensemble_mv": 99654.3881,
              "ensemble_all": 99935.2166,
              "unit": "Pa"
            },
            "RH2m": {
              "uv_HLSTM_GRU": 73.5448,
              "uv_GRU": 64.4683,
              "uv_ANN": 59.8685,
              "mv_HLSTM_GRU": 62.3084,
              "mv_GRU": 65.3955,
              "mv_ANN": 65.9636,
              "ensemble_uv": 65.9605,
              "ensemble_mv": 64.5558,
              "ensemble_all": 65.2582,
              "unit": "%"
            },
            "TMP2m": {
              "uv_HLSTM_GRU": 30.8273,
              "uv_GRU": 33.6692,
              "uv_ANN": 32.2281,
              "mv_HLSTM_GRU": 31.0858,
              "mv_GRU": 31.7529,
              "mv_ANN": 32.1176,
              "ensemble_uv": 32.2415,
              "ensemble_mv": 31.6521,
              "ensemble_all": 31.9468,
              "unit": "C"
            }
          }
        },
        {
          "horizon": 2,
          "forecast_date": "2026-07-02",
          "forecasts": {
            "PRmsl": {
              "uv_HLSTM_GRU": 100303.1413,
              "uv_GRU": 100272.7308,
              "uv_ANN": 100202.3486,
              "mv_HLSTM_GRU": 99741.885,
              "mv_GRU": 99322.9783,
              "mv_ANN": 99987.7135,
              "ensemble_uv": 100259.4069,
              "ensemble_mv": 99684.1922,
              "ensemble_all": 99971.7996,
              "unit": "Pa"
            },
            "RH2m": {
              "uv_HLSTM_GRU": 76.6855,
              "uv_GRU": 72.0295,
              "uv_ANN": 71.1062,
              "mv_HLSTM_GRU": 66.9147,
              "mv_GRU": 70.301,
              "mv_ANN": 70.5262,
              "ensemble_uv": 73.2737,
              "ensemble_mv": 69.2473,
              "ensemble_all": 71.2605,
              "unit": "%"
            },
            "TMP2m": {
              "uv_HLSTM_GRU": 28.9448,
              "uv_GRU": 31.7868,
              "uv_ANN": 31.1395,
              "mv_HLSTM_GRU": 30.7654,
              "mv_GRU": 31.2362,
              "mv_ANN": 31.8268,
              "ensemble_uv": 30.6237,
              "ensemble_mv": 31.2761,
              "ensemble_all": 30.9499,
              "unit": "C"
            }
          }
        },
        {
          "horizon": 3,
          "forecast_date": "2026-07-03",
          "forecasts": {
            "PRmsl": {
              "uv_HLSTM_GRU": 100310.0166,
              "uv_GRU": 100267.5727,
              "uv_ANN": 100222.1338,
              "mv_HLSTM_GRU": 99724.4435,
              "mv_GRU": 99348.055,
              "mv_ANN": 100006.1097,
              "ensemble_uv": 100266.5744,
              "ensemble_mv": 99692.8694,
              "ensemble_all": 99979.7219,
              "unit": "Pa"
            },
            "RH2m": {
              "uv_HLSTM_GRU": 78.8458,
              "uv_GRU": 75.6182,
              "uv_ANN": 76.4321,
              "mv_HLSTM_GRU": 69.3285,
              "mv_GRU": 72.4019,
              "mv_ANN": 71.9833,
              "ensemble_uv": 76.9654,
              "ensemble_mv": 71.2379,
              "ensemble_all": 74.1016,
              "unit": "%"
            },
            "TMP2m": {
              "uv_HLSTM_GRU": 29.6914,
              "uv_GRU": 30.809,
              "uv_ANN": 30.1591,
              "mv_HLSTM_GRU": 31.1653,
              "mv_GRU": 31.2152,
              "mv_ANN": 31.3151,
              "ensemble_uv": 30.2198,
              "ensemble_mv": 31.2319,
              "ensemble_all": 30.7258,
              "unit": "C"
            }
          }
        },
        {
          "horizon": 4,
          "forecast_date": "2026-07-04",
          "forecasts": {
            "PRmsl": {
              "uv_HLSTM_GRU": 100336.5369,
              "uv_GRU": 100274.5769,
              "uv_ANN": 100156.4219,
              "mv_HLSTM_GRU": 99743.3953,
              "mv_GRU": 99373.6942,
              "mv_ANN": 99988.0191,
              "ensemble_uv": 100255.8452,
              "ensemble_mv": 99701.7029,
              "ensemble_all": 99978.7741,
              "unit": "Pa"
            },
            "RH2m": {
              "uv_HLSTM_GRU": 78.1779,
              "uv_GRU": 76.4105,
              "uv_ANN": 76.3399,
              "mv_HLSTM_GRU": 70.1687,
              "mv_GRU": 72.135,
              "mv_ANN": 72.6393,
              "ensemble_uv": 76.9761,
              "ensemble_mv": 71.6477,
              "ensemble_all": 74.3119,
              "unit": "%"
            },
            "TMP2m": {
              "uv_HLSTM_GRU": 32.2085,
              "uv_GRU": 30.5888,
              "uv_ANN": 30.1809,
              "mv_HLSTM_GRU": 31.7016,
              "mv_GRU": 31.431,
              "mv_ANN": 31.0429,
              "ensemble_uv": 30.9927,
              "ensemble_mv": 31.3918,
              "ensemble_all": 31.1923,
              "unit": "C"
            }
          }
        },
        {
          "horizon": 5,
          "forecast_date": "2026-07-05",
          "forecasts": {
            "PRmsl": {
              "uv_HLSTM_GRU": 100332.9838,
              "uv_GRU": 100261.932,
              "uv_ANN": 100136.8876,
              "mv_HLSTM_GRU": 99706.1464,
              "mv_GRU": 99378.4436,
              "mv_ANN": 99973.7279,
              "ensemble_uv": 100243.9345,
              "ensemble_mv": 99686.106,
              "ensemble_all": 99965.0202,
              "unit": "Pa"
            },
            "RH2m": {
              "uv_HLSTM_GRU": 76.8898,
              "uv_GRU": 76.3785,
              "uv_ANN": 76.1092,
              "mv_HLSTM_GRU": 70.5894,
              "mv_GRU": 72.0064,
              "mv_ANN": 73.1672,
              "ensemble_uv": 76.4592,
              "ensemble_mv": 71.921,
              "ensemble_all": 74.1901,
              "unit": "%"
            },
            "TMP2m": {
              "uv_HLSTM_GRU": 34.4536,
              "uv_GRU": 31.0254,
              "uv_ANN": 30.5784,
              "mv_HLSTM_GRU": 32.2376,
              "mv_GRU": 31.7974,
              "mv_ANN": 31.2441,
              "ensemble_uv": 32.0191,
              "ensemble_mv": 31.7597,
              "ensemble_all": 31.8894,
              "unit": "C"
            }
          }
        }
      ]
    },
    "Chennai": {
      "lat": 13.08,
      "lon": 80.27,
      "horizons": [
        {
          "horizon": 1,
          "forecast_date": "2026-07-01",
          "forecasts": {
            "PRmsl": {
              "uv_HLSTM_GRU": 100569.0529,
              "uv_GRU": 100519.0694,
              "uv_ANN": 100501.8195,
              "mv_HLSTM_GRU": 100524.8955,
              "mv_GRU": 100559.2896,
              "mv_ANN": 100517.8889,
              "ensemble_uv": 100529.9806,
              "ensemble_mv": 100534.0247,
              "ensemble_all": 100532.0026,
              "unit": "Pa"
            },
            "RH2m": {
              "uv_HLSTM_GRU": 66.5738,
              "uv_GRU": 63.6187,
              "uv_ANN": 66.3321,
              "mv_HLSTM_GRU": 65.1974,
              "mv_GRU": 65.2177,
              "mv_ANN": 68.4129,
              "ensemble_uv": 65.5082,
              "ensemble_mv": 66.276,
              "ensemble_all": 65.8921,
              "unit": "%"
            },
            "TMP2m": {
              "uv_HLSTM_GRU": 30.5733,
              "uv_GRU": 30.5485,
              "uv_ANN": 30.7079,
              "mv_HLSTM_GRU": 31.662,
              "mv_GRU": 31.3658,
              "mv_ANN": 31.4174,
              "ensemble_uv": 30.6099,
              "ensemble_mv": 31.4817,
              "ensemble_all": 31.0458,
              "unit": "C"
            }
          }
        },
        {
          "horizon": 2,
          "forecast_date": "2026-07-02",
          "forecasts": {
            "PRmsl": {
              "uv_HLSTM_GRU": 100540.6332,
              "uv_GRU": 100504.3464,
              "uv_ANN": 100534.3066,
              "mv_HLSTM_GRU": 100504.7854,
              "mv_GRU": 100505.4223,
              "mv_ANN": 100501.6119,
              "ensemble_uv": 100526.4287,
              "ensemble_mv": 100503.9399,
              "ensemble_all": 100515.1843,
              "unit": "Pa"
            },
            "RH2m": {
              "uv_HLSTM_GRU": 68.4985,
              "uv_GRU": 66.99,
              "uv_ANN": 67.1681,
              "mv_HLSTM_GRU": 66.6314,
              "mv_GRU": 66.2158,
              "mv_ANN": 67.8112,
              "ensemble_uv": 67.5522,
              "ensemble_mv": 66.8861,
              "ensemble_all": 67.2192,
              "unit": "%"
            },
            "TMP2m": {
              "uv_HLSTM_GRU": 30.6745,
              "uv_GRU": 30.656,
              "uv_ANN": 31.0055,
              "mv_HLSTM_GRU": 31.5304,
              "mv_GRU": 31.362,
              "mv_ANN": 31.4095,
              "ensemble_uv": 30.7787,
              "ensemble_mv": 31.434,
              "ensemble_all": 31.1063,
              "unit": "C"
            }
          }
        },
        {
          "horizon": 3,
          "forecast_date": "2026-07-03",
          "forecasts": {
            "PRmsl": {
              "uv_HLSTM_GRU": 100541.4387,
              "uv_GRU": 100483.0254,
              "uv_ANN": 100527.9259,
              "mv_HLSTM_GRU": 100509.6692,
              "mv_GRU": 100524.8691,
              "mv_ANN": 100489.9206,
              "ensemble_uv": 100517.4633,
              "ensemble_mv": 100508.153,
              "ensemble_all": 100512.8081,
              "unit": "Pa"
            },
            "RH2m": {
              "uv_HLSTM_GRU": 70.1113,
              "uv_GRU": 68.2938,
              "uv_ANN": 69.1238,
              "mv_HLSTM_GRU": 67.4577,
              "mv_GRU": 67.111,
              "mv_ANN": 66.7501,
              "ensemble_uv": 69.1763,
              "ensemble_mv": 67.1062,
              "ensemble_all": 68.1413,
              "unit": "%"
            },
            "TMP2m": {
              "uv_HLSTM_GRU": 30.4747,
              "uv_GRU": 30.5341,
              "uv_ANN": 30.919,
              "mv_HLSTM_GRU": 31.4595,
              "mv_GRU": 31.3057,
              "mv_ANN": 31.5247,
              "ensemble_uv": 30.6426,
              "ensemble_mv": 31.43,
              "ensemble_all": 31.0363,
              "unit": "C"
            }
          }
        },
        {
          "horizon": 4,
          "forecast_date": "2026-07-04",
          "forecasts": {
            "PRmsl": {
              "uv_HLSTM_GRU": 100554.3626,
              "uv_GRU": 100493.8539,
              "uv_ANN": 100521.49,
              "mv_HLSTM_GRU": 100504.1624,
              "mv_GRU": 100509.7339,
              "mv_ANN": 100498.1096,
              "ensemble_uv": 100523.2355,
              "ensemble_mv": 100504.0019,
              "ensemble_all": 100513.6187,
              "unit": "Pa"
            },
            "RH2m": {
              "uv_HLSTM_GRU": 70.9609,
              "uv_GRU": 69.4161,
              "uv_ANN": 70.3874,
              "mv_HLSTM_GRU": 67.7055,
              "mv_GRU": 67.5959,
              "mv_ANN": 68.2237,
              "ensemble_uv": 70.2548,
              "ensemble_mv": 67.8417,
              "ensemble_all": 69.0482,
              "unit": "%"
            },
            "TMP2m": {
              "uv_HLSTM_GRU": 30.2306,
              "uv_GRU": 30.442,
              "uv_ANN": 30.8807,
              "mv_HLSTM_GRU": 31.344,
              "mv_GRU": 31.2523,
              "mv_ANN": 31.5758,
              "ensemble_uv": 30.5178,
              "ensemble_mv": 31.3907,
              "ensemble_all": 30.9542,
              "unit": "C"
            }
          }
        },
        {
          "horizon": 5,
          "forecast_date": "2026-07-05",
          "forecasts": {
            "PRmsl": {
              "uv_HLSTM_GRU": 100553.8579,
              "uv_GRU": 100482.0836,
              "uv_ANN": 100509.7596,
              "mv_HLSTM_GRU": 100513.4092,
              "mv_GRU": 100518.4911,
              "mv_ANN": 100500.133,
              "ensemble_uv": 100515.2337,
              "ensemble_mv": 100510.6778,
              "ensemble_all": 100512.9557,
              "unit": "Pa"
            },
            "RH2m": {
              "uv_HLSTM_GRU": 71.075,
              "uv_GRU": 70.1468,
              "uv_ANN": 71.1013,
              "mv_HLSTM_GRU": 67.3807,
              "mv_GRU": 66.9961,
              "mv_ANN": 68.6899,
              "ensemble_uv": 70.7744,
              "ensemble_mv": 67.6889,
              "ensemble_all": 69.2316,
              "unit": "%"
            },
            "TMP2m": {
              "uv_HLSTM_GRU": 30.0967,
              "uv_GRU": 30.4324,
              "uv_ANN": 30.7372,
              "mv_HLSTM_GRU": 31.3039,
              "mv_GRU": 31.2011,
              "mv_ANN": 31.5038,
              "ensemble_uv": 30.4221,
              "ensemble_mv": 31.3363,
              "ensemble_all": 30.8792,
              "unit": "C"
            }
          }
        }
      ]
    }
  }
}